{    
    "menulist" : [
        {
            "name": "Home",
            "id" : "001",
            "isHeaderMenu": false
        },
        {
            "name" : "Notes",
            "id": "100",
            "isHeaderMenu": false,
            "submenu" : [
                {
                    "name": "Java",
                    "isHeaderMenu":false,
                    "submenu": [
                        {
                            "name": "OOP Concepts",
                            "id": "101"
                        },
                        {
                            "name": "Serializations",
                            "id": "102"
                        }
                    ]
                }
            ]
        },
        {
            "name": "Blog",
            "id" : "200",
            "isHeaderMenu": true,
            "submenu" : [
                {
                    "id": "201",
                    "name": "How I Created this website?",
                    "isHeaderMenu":false                                    
                },
                {
                    "id": "202",
                    "name": "Design of this website",
                    "isHeaderMenu":false 
                }
            ]
        },
        {
            "id": "401",
            "name": "About",
            "isHeaderMenu": true
        }  
    ]  
    
}